defer/__init__.py
defer/__init__.pyi
py_defer-1.3.0.dist-info/LICENSE
py_defer-1.3.0.dist-info/METADATA
py_defer-1.3.0.dist-info/WHEEL
py_defer-1.3.0.dist-info/top_level.txt
py_defer-1.3.0.dist-info/RECORD
