Metadata-Version: 2.1
Name: py-defer
Version: 1.3.0
Summary: Golang-esque defer functionality
Home-page: http://github.com/naphta/with-defer
Author: Jake Hill
Author-email: jake@naphta.uk
License: MIT
Platform: UNKNOWN
Classifier: Intended Audience :: Developers
Classifier: License :: OSI Approved :: MIT License
Classifier: Programming Language :: Python
Classifier: Programming Language :: Python :: 3
Classifier: Programming Language :: Python :: 3.6
Classifier: Programming Language :: Python :: 3.7
Classifier: Programming Language :: Python :: Implementation :: CPython
Requires-Python: >=3.6
